[{ "_id" : { "$oid" : "50002e1e33679d0c5f9be6aa" }, "profile" : { "coders" : [ "aleyz", "micspa", "admin" ], "index" : 1, "shuffle" : false, "name" : "Batch 1", "created_at" : { "$date" : 1342171086827 }, "codebook_id" : { "$oid" : "500020db33679d0a2dd4ca89" }, "collection_id" : { "$oid" : "50002c1a33679d0c5f9be6a7" }, "pct_overlap" : 100, "description" : "News sample A * Opinion (2)" }, "documents" : [ { "index" : 0, "labels" : { "admin" : [ { "created_at" : { "$date" : 1342186518607 }, "Q2_notes" : "", "Q1_opinion" : "1" }, { "created_at" : { "$date" : 1342188103556 }, "Q2_notes" : "" } ], "aleyz" : [ { "created_at" : { "$date" : 1342189570003 }, "Q2_notes" : "", "Q1_opinion" : "1" } ], "micspa" : [ { "created_at" : { "$date" : 1342446873676 }, "Q2_notes" : "", "Q1_opinion" : "1" } ] } }, { "index" : 1, "labels" : { "admin" : [ { "created_at" : { "$date" : 1342186557947 }, "Q2_notes" : "Not much \"opinion,\" but it's definitely in the first person.", "Q1_opinion" : "1" } ], "aleyz" : [ { "created_at" : { "$date" : 1342472079442 }, "Q2_notes" : "", "Q1_opinion" : "2" } ], "micspa" : [ { "created_at" : { "$date" : 1342447020491 }, "Q2_notes" : "", "Q1_opinion" : "3" } ] } }, { "index" : 2, "labels" : { "admin" : [ { "created_at" : { "$date" : 1342186628587 }, "Q2_notes" : "This is the most random thing I've ever seen in a news article.", "Q1_opinion" : "3" } ], "aleyz" : [ { "created_at" : { "$date" : 1342472153273 }, "Q2_notes" : "", "Q1_opinion" : "3" } ], "micspa" : [ { "created_at" : { "$date" : 1342447063381 }, "Q2_notes" : "", "Q1_opinion" : "3" } ] } }, { "index" : 3, "labels" : { "admin" : [ { "created_at" : { "$date" : 1342186631091 }, "Q2_notes" : "" } ], "aleyz" : [ { "created_at" : { "$date" : 1342472167683 }, "Q2_notes" : "No text", "Q1_opinion" : "3" } ], "micspa" : [ { "created_at" : { "$date" : 1342447067588 }, "Q2_notes" : "" } ] } }, { "index" : 4, "labels" : { "admin" : [ { "created_at" : { "$date" : 1342186639024 }, "Q2_notes" : "", "Q1_opinion" : "3" } ], "aleyz" : [ { "created_at" : { "$date" : 1342472263613 }, "Q2_notes" : "", "Q1_opinion" : "3" } ], "micspa" : [ { "created_at" : { "$date" : 1342447088902 }, "Q2_notes" : "", "Q1_opinion" : "3" } ] } }, { "index" : 5, "labels" : { "admin" : [ { "created_at" : { "$date" : 1342186642492 }, "Q2_notes" : "" } ], "aleyz" : [ { "created_at" : { "$date" : 1342472275990 }, "Q2_notes" : "Not enough text", "Q1_opinion" : "3" } ], "micspa" : [ { "created_at" : { "$date" : 1342447095888 }, "Q2_notes" : "" } ] } }, { "index" : 6, "labels" : { "admin" : [ { "created_at" : { "$date" : 1342186653446 }, "Q2_notes" : "", "Q1_opinion" : "3" } ], "aleyz" : [ { "created_at" : { "$date" : 1342472452227 }, "Q2_notes" : "", "Q1_opinion" : "3" } ], "micspa" : [ { "created_at" : { "$date" : 1342447164809 }, "Q2_notes" : "", "Q1_opinion" : "3" } ] } }, { "index" : 7, "labels" : { "admin" : [ { "created_at" : { "$date" : 1342186664410 }, "Q2_notes" : "", "Q1_opinion" : "3" } ], "aleyz" : [ { "created_at" : { "$date" : 1342472642482 }, "Q2_notes" : "", "Q1_opinion" : "3" } ], "micspa" : [ { "created_at" : { "$date" : 1342447206205 }, "Q2_notes" : "", "Q1_opinion" : "3" } ] } }, { "index" : 8, "labels" : { "admin" : [ { "created_at" : { "$date" : 1342186702789 }, "Q2_notes" : "", "Q1_opinion" : "2" } ], "aleyz" : [ { "created_at" : { "$date" : 1342472830127 }, "Q2_notes" : "", "Q1_opinion" : "3" } ], "micspa" : [ { "created_at" : { "$date" : 1342447232790 }, "Q2_notes" : "", "Q1_opinion" : "3" } ] } }, { "index" : 9, "labels" : { "admin" : [ { "created_at" : { "$date" : 1342186720247 }, "Q2_notes" : "", "Q1_opinion" : "3" } ], "aleyz" : [ { "created_at" : { "$date" : 1342472940902 }, "Q2_notes" : "", "Q1_opinion" : "3" } ], "micspa" : [ { "created_at" : { "$date" : 1342447251756 }, "Q2_notes" : "", "Q1_opinion" : "3" } ] } }, { "index" : 10, "labels" : { "admin" : [ { "created_at" : { "$date" : 1342186775896 }, "Q2_notes" : "\"Is this article written in a neutral, third-person voice?\"\r\n*Yes...\r\n*Yes, but ...\r\n* No, but...\r\n* No..." } ], "aleyz" : [ { "created_at" : { "$date" : 1342473070073 }, "Q2_notes" : "", "Q1_opinion" : "3" } ], "micspa" : [ { "created_at" : { "$date" : 1342447296030 }, "Q2_notes" : "", "Q1_opinion" : "3" } ] } }, { "index" : 11, "labels" : { "admin" : [ { "created_at" : { "$date" : 1342186797779 }, "Q2_notes" : "", "Q1_opinion" : "3" } ], "aleyz" : [ { "created_at" : { "$date" : 1342473232485 }, "Q2_notes" : "", "Q1_opinion" : "2" } ], "micspa" : [ { "created_at" : { "$date" : 1342447398914 }, "Q2_notes" : "", "Q1_opinion" : "1" } ] } }, { "index" : 12, "labels" : { "admin" : [ { "created_at" : { "$date" : 1342186803198 }, "Q2_notes" : "", "Q1_opinion" : "3" } ], "aleyz" : [ { "created_at" : { "$date" : 1342473594313 }, "Q2_notes" : "", "Q1_opinion" : "3" } ], "micspa" : [ { "created_at" : { "$date" : 1342447411673 }, "Q2_notes" : "", "Q1_opinion" : "3" } ] } }, { "index" : 13, "labels" : { "admin" : [ { "created_at" : { "$date" : 1342186804993 }, "Q2_notes" : "" } ], "aleyz" : [ { "created_at" : { "$date" : 1342473603034 }, "Q2_notes" : "No text", "Q1_opinion" : "3" } ], "micspa" : [ { "created_at" : { "$date" : 1342447413397 }, "Q2_notes" : "" } ] } }, { "index" : 14, "labels" : { "admin" : [ { "created_at" : { "$date" : 1342186818134 }, "Q2_notes" : "", "Q1_opinion" : "3" } ], "aleyz" : [ { "created_at" : { "$date" : 1342475677171 }, "Q2_notes" : "", "Q1_opinion" : "3" } ], "micspa" : [ { "created_at" : { "$date" : 1342447421559 }, "Q2_notes" : "", "Q1_opinion" : "3" } ] } }, { "index" : 15, "labels" : { "admin" : [ { "created_at" : { "$date" : 1342186857994 }, "Q2_notes" : "", "Q1_opinion" : "1" } ], "aleyz" : [ { "created_at" : { "$date" : 1342475946882 }, "Q2_notes" : "", "Q1_opinion" : "1" } ], "micspa" : [ { "created_at" : { "$date" : 1342447469812 }, "Q2_notes" : "", "Q1_opinion" : "1" } ] } }, { "index" : 16, "labels" : { "admin" : [ { "created_at" : { "$date" : 1342186896406 }, "Q2_notes" : "", "Q1_opinion" : "2" } ], "aleyz" : [ { "created_at" : { "$date" : 1342476147786 }, "Q2_notes" : "", "Q1_opinion" : "1" } ], "micspa" : [ { "created_at" : { "$date" : 1342447524060 }, "Q2_notes" : "", "Q1_opinion" : "1" } ] } }, { "index" : 17, "labels" : { "admin" : [ { "created_at" : { "$date" : 1342186915925 }, "Q2_notes" : "", "Q1_opinion" : "1" } ], "aleyz" : [ { "created_at" : { "$date" : 1342476333535 }, "Q2_notes" : "", "Q1_opinion" : "3" } ], "micspa" : [ { "created_at" : { "$date" : 1342447594148 }, "Q2_notes" : "", "Q1_opinion" : "1" } ] } }, { "index" : 18, "labels" : { "admin" : [ { "created_at" : { "$date" : 1342186966090 }, "Q2_notes" : "", "Q1_opinion" : "3" } ], "aleyz" : [ { "created_at" : { "$date" : 1342476554202 }, "Q2_notes" : "", "Q1_opinion" : "3" } ], "micspa" : [ { "created_at" : { "$date" : 1342447702019 }, "Q2_notes" : "", "Q1_opinion" : "3" } ] } }, { "index" : 19, "labels" : { "admin" : [ { "created_at" : { "$date" : 1342186982424 }, "Q2_notes" : "", "Q1_opinion" : "3" }, { "created_at" : { "$date" : 1342186987654 }, "Q2_notes" : "", "Q1_opinion" : "3" } ], "aleyz" : [ { "created_at" : { "$date" : 1342476607592 }, "Q2_notes" : "", "Q1_opinion" : "3" }, { "created_at" : { "$date" : 1342476615773 }, "Q2_notes" : "", "Q1_opinion" : "3" } ], "micspa" : [ { "created_at" : { "$date" : 1342447725462 }, "Q2_notes" : "", "Q1_opinion" : "3" } ] } } ], "reports" : { "progress" : { "coders" : { "admin" : { "assigned" : 20, "percent" : 100, "complete" : 20 }, "aleyz" : { "assigned" : 20, "percent" : 100, "complete" : 20 }, "micspa" : { "assigned" : 20, "percent" : 100, "complete" : 20 } }, "summary" : { "assigned" : 60, "percent" : 100, "complete" : 60 } }, "reliability" : {} } },{ "_id" : { "$oid" : "5000446033679d0c5f9be6bf" }, "profile" : { "coders" : [ "aleyz", "micspa", "admin" ], "index" : 2, "shuffle" : false, "name" : "Batch 2", "created_at" : { "$date" : 1342176784115 }, "codebook_id" : { "$oid" : "50003c9033679d0c5f9be6b8" }, "collection_id" : { "$oid" : "50002c1a33679d0c5f9be6a7" }, "pct_overlap" : 100, "description" : "News sample A * Public Import (3)" }, "documents" : [ { "index" : 0, "labels" : { "admin" : [], "aleyz" : [ { "Q1_mchoice" : "1", "created_at" : { "$date" : 1342512796156 }, "Q2_mchoice" : "2", "Q3_notes" : "" } ], "micspa" : [] } }, { "index" : 1, "labels" : { "admin" : [], "aleyz" : [ { "Q1_mchoice" : "1", "created_at" : { "$date" : 1342512818301 }, "Q2_mchoice" : "2", "Q3_notes" : "" } ], "micspa" : [] } }, { "index" : 2, "labels" : { "admin" : [], "aleyz" : [ { "Q1_mchoice" : "1", "created_at" : { "$date" : 1342512839220 }, "Q2_mchoice" : "2", "Q3_notes" : "" } ], "micspa" : [] } }, { "index" : 3, "labels" : { "admin" : [], "aleyz" : [ { "Q1_mchoice" : "2", "created_at" : { "$date" : 1342512853037 }, "Q2_mchoice" : "2", "Q3_notes" : "No text" } ], "micspa" : [] } }, { "index" : 4, "labels" : { "admin" : [], "aleyz" : [ { "Q1_mchoice" : "1", "created_at" : { "$date" : 1342512882805 }, "Q2_mchoice" : "2", "Q3_notes" : "" } ], "micspa" : [] } }, { "index" : 5, "labels" : { "admin" : [], "aleyz" : [ { "Q1_mchoice" : "2", "created_at" : { "$date" : 1342512897491 }, "Q2_mchoice" : "2", "Q3_notes" : "No text" } ], "micspa" : [] } }, { "index" : 6, "labels" : { "admin" : [], "aleyz" : [ { "Q1_mchoice" : "2", "created_at" : { "$date" : 1342513024905 }, "Q2_mchoice" : "2", "Q3_notes" : "" } ], "micspa" : [] } }, { "index" : 7, "labels" : { "admin" : [], "aleyz" : [ { "Q1_mchoice" : "1", "created_at" : { "$date" : 1342513099232 }, "Q2_mchoice" : "2", "Q3_notes" : "I think this topic requires collective action by the team members and coaches. " } ], "micspa" : [] } }, { "index" : 8, "labels" : { "admin" : [], "aleyz" : [ { "Q1_mchoice" : "1", "created_at" : { "$date" : 1342513122753 }, "Q2_mchoice" : "1", "Q3_notes" : "" } ], "micspa" : [] } }, { "index" : 9, "labels" : { "admin" : [], "aleyz" : [ { "Q1_mchoice" : "2", "created_at" : { "$date" : 1342513146579 }, "Q2_mchoice" : "3", "Q3_notes" : "" } ], "micspa" : [] } }, { "index" : 10, "labels" : { "admin" : [], "aleyz" : [ { "Q1_mchoice" : "2", "created_at" : { "$date" : 1342513376780 }, "Q2_mchoice" : "3", "Q3_notes" : "" } ], "micspa" : [] } }, { "index" : 11, "labels" : { "admin" : [], "aleyz" : [ { "Q1_mchoice" : "2", "created_at" : { "$date" : 1342513401939 }, "Q2_mchoice" : "3", "Q3_notes" : "" } ], "micspa" : [] } }, { "index" : 12, "labels" : { "admin" : [], "aleyz" : [ { "Q1_mchoice" : "3", "created_at" : { "$date" : 1342513409836 }, "Q2_mchoice" : "3", "Q3_notes" : "" } ], "micspa" : [] } }, { "index" : 13, "labels" : { "admin" : [], "aleyz" : [ { "Q1_mchoice" : "2", "created_at" : { "$date" : 1342513419686 }, "Q2_mchoice" : "2", "Q3_notes" : "No text" } ], "micspa" : [] } }, { "index" : 14, "labels" : { "admin" : [], "aleyz" : [ { "created_at" : { "$date" : 1342513429430 }, "Q2_mchoice" : "1", "Q3_notes" : "" } ], "micspa" : [] } }, { "index" : 15, "labels" : { "admin" : [], "aleyz" : [ { "Q1_mchoice" : "2", "created_at" : { "$date" : 1342513507912 }, "Q2_mchoice" : "1", "Q3_notes" : "Does the death of a national celebrity emotionally impact a substantial part of society? (i.e. death of Michael Jackson?) " } ], "micspa" : [] } }, { "index" : 16, "labels" : { "admin" : [], "aleyz" : [ { "Q1_mchoice" : "1", "created_at" : { "$date" : 1342513522354 }, "Q2_mchoice" : "1", "Q3_notes" : "" } ], "micspa" : [] } }, { "index" : 17, "labels" : { "admin" : [], "aleyz" : [ { "Q1_mchoice" : "2", "created_at" : { "$date" : 1342513536288 }, "Q2_mchoice" : "1", "Q3_notes" : "" } ], "micspa" : [] } }, { "index" : 18, "labels" : { "admin" : [], "aleyz" : [ { "Q1_mchoice" : "2", "created_at" : { "$date" : 1342513592094 }, "Q2_mchoice" : "2", "Q3_notes" : "Requires collective response from healthcare industry. " } ], "micspa" : [] } }, { "index" : 19, "labels" : { "admin" : [], "aleyz" : [ { "Q1_mchoice" : "1", "created_at" : { "$date" : 1342513599429 }, "Q2_mchoice" : "1", "Q3_notes" : "" }, { "Q1_mchoice" : "1", "created_at" : { "$date" : 1342513606273 }, "Q2_mchoice" : "1", "Q3_notes" : "" } ], "micspa" : [] } } ], "reports" : { "progress" : { "coders" : { "admin" : { "assigned" : 20, "percent" : 0, "complete" : 0 }, "aleyz" : { "assigned" : 20, "percent" : 100, "complete" : 20 }, "micspa" : { "assigned" : 20, "percent" : 0, "complete" : 0 } }, "summary" : { "assigned" : 60, "percent" : 33.3, "complete" : 20 } }, "reliability" : {} } },{ "_id" : { "$oid" : "500044ba33679d0c5f9be6c1" }, "profile" : { "coders" : [ "aleyz", "micspa", "admin" ], "index" : 3, "shuffle" : true, "name" : "Batch 3", "created_at" : { "$date" : 1342176874609 }, "codebook_id" : { "$oid" : "50003f7733679d0c5f9be6ba" }, "collection_id" : { "$oid" : "500044a033679d0c5f9be6c0" }, "pct_overlap" : 40, "description" : "News sample B * Codable (3)" }, "documents" : [ { "index" : 46, "labels" : { "micspa" : [ { "created_at" : { "$date" : 1342447798565 }, "Q3_essay" : "", "Q1_codable" : "1" } ] } }, { "index" : 42, "labels" : { "admin" : [], "aleyz" : [ { "created_at" : { "$date" : 1342476704222 }, "Q3_essay" : "", "Q1_codable" : "1" } ], "micspa" : [ { "created_at" : { "$date" : 1342447803048 }, "Q3_essay" : "", "Q1_codable" : "1" } ] } }, { "index" : 143, "labels" : { "admin" : [], "aleyz" : [ { "created_at" : { "$date" : 1342476720624 }, "Q3_essay" : "", "Q1_codable" : "1" } ], "micspa" : [ { "created_at" : { "$date" : 1342447807480 }, "Q3_essay" : "", "Q1_codable" : "1" } ] } }, { "index" : 8, "labels" : { "admin" : [] } }, { "index" : 5, "labels" : { "admin" : [] } }, { "index" : 6, "labels" : { "admin" : [], "aleyz" : [ { "created_at" : { "$date" : 1342476735767 }, "Q3_essay" : "", "Q1_codable" : "1" } ], "micspa" : [ { "created_at" : { "$date" : 1342447813088 }, "Q3_essay" : "", "Q1_codable" : "1" } ] } }, { "index" : 69, "labels" : { "aleyz" : [ { "created_at" : { "$date" : 1342476742676 }, "Q3_essay" : "", "Q1_codable" : "1" } ] } }, { "index" : 153, "labels" : { "aleyz" : [ { "created_at" : { "$date" : 1342507628603 }, "Q3_essay" : "The RELATED articles chop up the text, but it's a very minor issue", "Q1_codable" : "1" } ] } }, { "index" : 86, "labels" : { "admin" : [] } }, { "index" : 71, "labels" : { "admin" : [] } }, { "index" : 47, "labels" : { "admin" : [] } }, { "index" : 49, "labels" : { "micspa" : [ { "created_at" : { "$date" : 1342447816991 }, "Q3_essay" : "", "Q1_codable" : "1" } ] } }, { "index" : 118, "labels" : { "micspa" : [ { "created_at" : { "$date" : 1342447822836 }, "Q3_essay" : "", "Q1_codable" : "1" } ] } }, { "index" : 108, "labels" : { "aleyz" : [ { "created_at" : { "$date" : 1342507673912 }, "Q3_essay" : "", "Q1_codable" : "1" } ] } }, { "index" : 48, "labels" : { "admin" : [], "aleyz" : [ { "created_at" : { "$date" : 1342507682878 }, "Q3_essay" : "", "Q1_codable" : "1" } ], "micspa" : [ { "created_at" : { "$date" : 1342447826944 }, "Q3_essay" : "", "Q1_codable" : "1" } ] } }, { "index" : 158, "labels" : { "admin" : [] } }, { "index" : 168, "labels" : { "aleyz" : [ { "created_at" : { "$date" : 1342507687696 }, "Q3_essay" : "", "Q1_codable" : "1" } ] } }, { "index" : 106, "labels" : { "micspa" : [ { "created_at" : { "$date" : 1342447843791 }, "Q2_problem_type" : "1", "Q3_essay" : "", "Q1_codable" : "3" } ] } }, { "index" : 39, "labels" : { "admin" : [], "aleyz" : [ { "created_at" : { "$date" : 1342507707018 }, "Q3_essay" : "", "Q1_codable" : "1" } ], "micspa" : [ { "created_at" : { "$date" : 1342447847967 }, "Q3_essay" : "", "Q1_codable" : "1" } ] } }, { "index" : 50, "labels" : { "admin" : [] } }, { "index" : 159, "labels" : { "aleyz" : [ { "created_at" : { "$date" : 1342508598944 }, "Q3_essay" : "", "Q1_codable" : "1" } ] } }, { "index" : 116, "labels" : { "admin" : [] } }, { "index" : 21, "labels" : { "admin" : [], "aleyz" : [ { "created_at" : { "$date" : 1342508719268 }, "Q3_essay" : "", "Q1_codable" : "1" } ], "micspa" : [ { "created_at" : { "$date" : 1342447851933 }, "Q3_essay" : "", "Q1_codable" : "1" } ] } }, { "index" : 163, "labels" : { "admin" : [], "aleyz" : [ { "created_at" : { "$date" : 1342508727342 }, "Q3_essay" : "", "Q1_codable" : "1" } ], "micspa" : [ { "created_at" : { "$date" : 1342447855893 }, "Q3_essay" : "", "Q1_codable" : "1" } ] } }, { "index" : 104, "labels" : { "admin" : [], "aleyz" : [ { "created_at" : { "$date" : 1342508736817 }, "Q3_essay" : "", "Q1_codable" : "1" } ], "micspa" : [ { "created_at" : { "$date" : 1342447860296 }, "Q3_essay" : "", "Q1_codable" : "1" } ] } }, { "index" : 149, "labels" : { "admin" : [] } }, { "index" : 115, "labels" : { "micspa" : [ { "created_at" : { "$date" : 1342447863707 }, "Q3_essay" : "", "Q1_codable" : "1" } ] } }, { "index" : 40, "labels" : { "admin" : [], "aleyz" : [ { "created_at" : { "$date" : 1342508815606 }, "Q3_essay" : "", "Q1_codable" : "1" } ], "micspa" : [ { "created_at" : { "$date" : 1342447868662 }, "Q3_essay" : "", "Q1_codable" : "1" } ] } }, { "index" : 12, "labels" : { "aleyz" : [ { "created_at" : { "$date" : 1342509081180 }, "Q3_essay" : "", "Q1_codable" : "1" } ] } }, { "index" : 80, "labels" : { "admin" : [], "aleyz" : [ { "created_at" : { "$date" : 1342509191335 }, "Q3_essay" : "", "Q1_codable" : "1" } ], "micspa" : [ { "created_at" : { "$date" : 1342447873727 }, "Q3_essay" : "", "Q1_codable" : "1" } ] } }, { "index" : 16, "labels" : { "micspa" : [ { "created_at" : { "$date" : 1342447896137 }, "Q3_essay" : "", "Q1_codable" : "1" } ] } }, { "index" : 58, "labels" : { "micspa" : [ { "created_at" : { "$date" : 1342447899150 }, "Q3_essay" : "", "Q1_codable" : "1" } ] } }, { "index" : 154, "labels" : { "micspa" : [ { "created_at" : { "$date" : 1342447917270 }, "Q3_essay" : "", "Q1_codable" : "1" } ] } }, { "index" : 100, "labels" : { "admin" : [], "aleyz" : [ { "created_at" : { "$date" : 1342509197000 }, "Q2_problem_type" : "1", "Q3_essay" : "", "Q1_codable" : "3" } ], "micspa" : [ { "created_at" : { "$date" : 1342447923468 }, "Q2_problem_type" : "1", "Q3_essay" : "", "Q1_codable" : "3" } ] } }, { "index" : 75, "labels" : { "aleyz" : [ { "created_at" : { "$date" : 1342509201534 }, "Q2_problem_type" : "1", "Q3_essay" : "", "Q1_codable" : "3" } ] } }, { "index" : 179, "labels" : { "admin" : [], "aleyz" : [ { "created_at" : { "$date" : 1342509224840 }, "Q3_essay" : "", "Q1_codable" : "1" } ], "micspa" : [ { "created_at" : { "$date" : 1342447927277 }, "Q3_essay" : "", "Q1_codable" : "1" } ] } }, { "index" : 60, "labels" : { "aleyz" : [ { "created_at" : { "$date" : 1342509234256 }, "Q2_problem_type" : "1", "Q3_essay" : "", "Q1_codable" : "3" } ] } }, { "index" : 30, "labels" : { "aleyz" : [ { "created_at" : { "$date" : 1342509241062 }, "Q3_essay" : "", "Q1_codable" : "1" } ] } }, { "index" : 121, "labels" : { "admin" : [], "aleyz" : [ { "created_at" : { "$date" : 1342509267086 }, "Q3_essay" : "", "Q1_codable" : "1" } ], "micspa" : [ { "created_at" : { "$date" : 1342447944087 }, "Q3_essay" : "", "Q1_codable" : "1" } ] } }, { "index" : 92, "labels" : { "admin" : [] } }, { "index" : 171, "labels" : { "aleyz" : [ { "created_at" : { "$date" : 1342509276653 }, "Q3_essay" : "", "Q1_codable" : "1" } ] } }, { "index" : 175, "labels" : { "admin" : [], "aleyz" : [ { "created_at" : { "$date" : 1342509291321 }, "Q3_essay" : "", "Q1_codable" : "1" } ], "micspa" : [ { "created_at" : { "$date" : 1342447948863 }, "Q3_essay" : "", "Q1_codable" : "1" } ] } }, { "index" : 53, "labels" : { "admin" : [] } }, { "index" : 41, "labels" : { "admin" : [] } }, { "index" : 178, "labels" : { "admin" : [], "aleyz" : [ { "created_at" : { "$date" : 1342509374729 }, "Q3_essay" : "It's a little short but it's still possible to code ", "Q1_codable" : "1" } ], "micspa" : [ { "created_at" : { "$date" : 1342448039884 }, "Q3_essay" : "It seems like there should be more paragraphs in this news story, but they aren't showing up", "Q1_codable" : "2" } ] } }, { "index" : 120, "labels" : { "aleyz" : [ { "created_at" : { "$date" : 1342509536707 }, "Q3_essay" : "", "Q1_codable" : "1" } ] } }, { "index" : 141, "labels" : { "admin" : [], "aleyz" : [ { "created_at" : { "$date" : 1342509552507 }, "Q3_essay" : "", "Q1_codable" : "1" } ], "micspa" : [ { "created_at" : { "$date" : 1342448046156 }, "Q3_essay" : "", "Q1_codable" : "1" } ] } }, { "index" : 24, "labels" : { "admin" : [], "aleyz" : [ { "created_at" : { "$date" : 1342509626013 }, "Q3_essay" : "", "Q1_codable" : "1" } ], "micspa" : [ { "created_at" : { "$date" : 1342448051735 }, "Q3_essay" : "", "Q1_codable" : "1" } ] } }, { "index" : 20, "labels" : { "admin" : [] } }, { "index" : 133, "labels" : { "micspa" : [ { "created_at" : { "$date" : 1342448137521 }, "Q3_essay" : "It seems like there should be one or two more paragraphs at the end of this news story", "Q1_codable" : "2" } ] } }, { "index" : 174, "labels" : { "aleyz" : [ { "created_at" : { "$date" : 1342509675539 }, "Q3_essay" : "", "Q1_codable" : "1" } ] } }, { "index" : 176, "labels" : { "admin" : [], "aleyz" : [ { "created_at" : { "$date" : 1342509686067 }, "Q3_essay" : "", "Q1_codable" : "1" } ], "micspa" : [ { "created_at" : { "$date" : 1342448145505 }, "Q3_essay" : "", "Q1_codable" : "1" } ] } }, { "index" : 28, "labels" : { "admin" : [], "aleyz" : [ { "created_at" : { "$date" : 1342509708335 }, "Q3_essay" : "", "Q1_codable" : "1" } ], "micspa" : [ { "created_at" : { "$date" : 1342448150363 }, "Q3_essay" : "", "Q1_codable" : "1" } ] } }, { "index" : 66, "labels" : { "admin" : [], "aleyz" : [ { "created_at" : { "$date" : 1342509790313 }, "Q3_essay" : "", "Q1_codable" : "1" } ], "micspa" : [ { "created_at" : { "$date" : 1342448155190 }, "Q3_essay" : "", "Q1_codable" : "1" } ] } }, { "index" : 82, "labels" : { "micspa" : [ { "created_at" : { "$date" : 1342448187427 }, "Q3_essay" : "", "Q1_codable" : "1" } ] } }, { "index" : 52, "labels" : { "admin" : [], "aleyz" : [ { "created_at" : { "$date" : 1342509839441 }, "Q3_essay" : "", "Q1_codable" : "1" } ], "micspa" : [ { "created_at" : { "$date" : 1342448194063 }, "Q3_essay" : "", "Q1_codable" : "1" } ] } }, { "index" : 93, "labels" : { "admin" : [], "aleyz" : [ { "created_at" : { "$date" : 1342509843983 }, "Q3_essay" : "", "Q1_codable" : "1" } ], "micspa" : [ { "created_at" : { "$date" : 1342448201239 }, "Q3_essay" : "", "Q1_codable" : "1" } ] } }, { "index" : 1, "labels" : { "admin" : [], "aleyz" : [ { "created_at" : { "$date" : 1342509853800 }, "Q3_essay" : "", "Q1_codable" : "1" } ], "micspa" : [ { "created_at" : { "$date" : 1342448207511 }, "Q3_essay" : "", "Q1_codable" : "1" } ] } }, { "index" : 64, "labels" : { "micspa" : [ { "created_at" : { "$date" : 1342448215370 }, "Q3_essay" : "", "Q1_codable" : "1" } ] } }, { "index" : 157, "labels" : { "admin" : [], "aleyz" : [ { "created_at" : { "$date" : 1342509861087 }, "Q3_essay" : "", "Q1_codable" : "1" } ], "micspa" : [ { "created_at" : { "$date" : 1342448221034 }, "Q3_essay" : "", "Q1_codable" : "1" } ] } }, { "index" : 72, "labels" : { "aleyz" : [ { "created_at" : { "$date" : 1342509903238 }, "Q3_essay" : "", "Q1_codable" : "1" } ] } }, { "index" : 57, "labels" : { "aleyz" : [ { "created_at" : { "$date" : 1342509956468 }, "Q3_essay" : "", "Q1_codable" : "1" } ] } }, { "index" : 128, "labels" : { "admin" : [], "aleyz" : [ { "created_at" : { "$date" : 1342510044008 }, "Q3_essay" : "", "Q1_codable" : "1" } ], "micspa" : [ { "created_at" : { "$date" : 1342448224621 }, "Q3_essay" : "", "Q1_codable" : "1" } ] } }, { "index" : 2, "labels" : { "admin" : [] } }, { "index" : 177, "labels" : { "aleyz" : [ { "created_at" : { "$date" : 1342510123089 }, "Q3_essay" : "There's multiple spaces between many words ", "Q1_codable" : "1" } ] } }, { "index" : 160, "labels" : { "micspa" : [ { "created_at" : { "$date" : 1342448229993 }, "Q2_problem_type" : "1", "Q3_essay" : "", "Q1_codable" : "3" } ] } }, { "index" : 165, "labels" : { "admin" : [], "aleyz" : [ { "created_at" : { "$date" : 1342510132757 }, "Q3_essay" : "", "Q1_codable" : "1" } ], "micspa" : [ { "created_at" : { "$date" : 1342448282984 }, "Q3_essay" : "It seems like there should be one or two more paragraphs at the end of this news story", "Q1_codable" : "2" } ] } }, { "index" : 161, "labels" : { "admin" : [], "aleyz" : [ { "created_at" : { "$date" : 1342510139122 }, "Q3_essay" : "", "Q1_codable" : "1" } ], "micspa" : [ { "created_at" : { "$date" : 1342448289080 }, "Q3_essay" : "", "Q1_codable" : "1" } ] } }, { "index" : 152, "labels" : { "admin" : [], "aleyz" : [ { "created_at" : { "$date" : 1342510143714 }, "Q3_essay" : "", "Q1_codable" : "1" } ], "micspa" : [ { "created_at" : { "$date" : 1342448292317 }, "Q3_essay" : "", "Q1_codable" : "1" } ] } }, { "index" : 9, "labels" : { "admin" : [], "aleyz" : [ { "created_at" : { "$date" : 1342510150163 }, "Q2_problem_type" : "1", "Q3_essay" : "", "Q1_codable" : "3" } ], "micspa" : [ { "created_at" : { "$date" : 1342448297464 }, "Q2_problem_type" : "1", "Q3_essay" : "", "Q1_codable" : "3" } ] } }, { "index" : 18, "labels" : { "admin" : [], "aleyz" : [ { "created_at" : { "$date" : 1342510159909 }, "Q3_essay" : "", "Q1_codable" : "1" } ], "micspa" : [ { "created_at" : { "$date" : 1342448310498 }, "Q3_essay" : "", "Q1_codable" : "1" } ] } }, { "index" : 164, "labels" : { "admin" : [] } }, { "index" : 125, "labels" : { "admin" : [] } }, { "index" : 119, "labels" : { "admin" : [] } }, { "index" : 137, "labels" : { "admin" : [], "aleyz" : [ { "created_at" : { "$date" : 1342510184867 }, "Q3_essay" : "", "Q1_codable" : "1" } ], "micspa" : [ { "created_at" : { "$date" : 1342448333910 }, "Q3_essay" : "", "Q1_codable" : "1" } ] } }, { "index" : 29, "labels" : { "admin" : [], "aleyz" : [ { "created_at" : { "$date" : 1342510241933 }, "Q3_essay" : "", "Q1_codable" : "1" } ], "micspa" : [ { "created_at" : { "$date" : 1342448341407 }, "Q3_essay" : "", "Q1_codable" : "1" } ] } }, { "index" : 34, "labels" : { "admin" : [], "aleyz" : [ { "created_at" : { "$date" : 1342510274810 }, "Q3_essay" : "", "Q1_codable" : "1" } ], "micspa" : [ { "created_at" : { "$date" : 1342448343987 }, "Q3_essay" : "", "Q1_codable" : "1" } ] } }, { "index" : 17, "labels" : { "admin" : [], "aleyz" : [ { "created_at" : { "$date" : 1342510281376 }, "Q2_problem_type" : "1", "Q3_essay" : "", "Q1_codable" : "3" } ], "micspa" : [ { "created_at" : { "$date" : 1342448348998 }, "Q2_problem_type" : "1", "Q3_essay" : "", "Q1_codable" : "3" } ] } }, { "index" : 173, "labels" : { "admin" : [] } }, { "index" : 145, "labels" : { "micspa" : [ { "created_at" : { "$date" : 1342448372599 }, "Q3_essay" : "It seems like there are several paragraphs missing", "Q1_codable" : "3" } ] } }, { "index" : 76, "labels" : { "admin" : [], "aleyz" : [ { "created_at" : { "$date" : 1342510288987 }, "Q3_essay" : "", "Q1_codable" : "1" } ], "micspa" : [ { "created_at" : { "$date" : 1342448378028 }, "Q3_essay" : "", "Q1_codable" : "1" } ] } }, { "index" : 55, "labels" : { "micspa" : [ { "created_at" : { "$date" : 1342448385279 }, "Q3_essay" : "", "Q1_codable" : "1" } ] } }, { "index" : 73, "labels" : { "admin" : [], "aleyz" : [ { "created_at" : { "$date" : 1342510294704 }, "Q3_essay" : "", "Q1_codable" : "1" } ], "micspa" : [ { "created_at" : { "$date" : 1342448417889 }, "Q3_essay" : "", "Q1_codable" : "1" } ] } }, { "index" : 65, "labels" : { "admin" : [], "aleyz" : [ { "created_at" : { "$date" : 1342510300308 }, "Q3_essay" : "", "Q1_codable" : "1" } ], "micspa" : [ { "created_at" : { "$date" : 1342448422476 }, "Q3_essay" : "", "Q1_codable" : "1" } ] } }, { "index" : 54, "labels" : { "admin" : [], "aleyz" : [ { "created_at" : { "$date" : 1342510331828 }, "Q3_essay" : "", "Q1_codable" : "1" } ], "micspa" : [ { "created_at" : { "$date" : 1342448540583 }, "Q3_essay" : "It seems like there should be one or two more paragraphs at the end of this news story", "Q1_codable" : "2" } ] } }, { "index" : 102, "labels" : { "aleyz" : [ { "created_at" : { "$date" : 1342510369139 }, "Q2_problem_type" : "1", "Q3_essay" : "", "Q1_codable" : "3" } ] } }, { "index" : 61, "labels" : { "admin" : [], "aleyz" : [ { "created_at" : { "$date" : 1342510379462 }, "Q3_essay" : "", "Q1_codable" : "1" } ], "micspa" : [ { "created_at" : { "$date" : 1342448546527 }, "Q3_essay" : "", "Q1_codable" : "1" } ] } }, { "index" : 111, "labels" : { "aleyz" : [ { "created_at" : { "$date" : 1342510422854 }, "Q3_essay" : "", "Q1_codable" : "1" } ] } }, { "index" : 25, "labels" : { "micspa" : [ { "created_at" : { "$date" : 1342448549804 }, "Q3_essay" : "", "Q1_codable" : "1" } ] } }, { "index" : 99, "labels" : { "aleyz" : [ { "created_at" : { "$date" : 1342510427326 }, "Q2_problem_type" : "1", "Q3_essay" : "", "Q1_codable" : "3" } ] } }, { "index" : 142, "labels" : { "micspa" : [ { "created_at" : { "$date" : 1342448556004 }, "Q3_essay" : "", "Q1_codable" : "1" } ] } }, { "index" : 138, "labels" : { "aleyz" : [ { "created_at" : { "$date" : 1342510490022 }, "Q3_essay" : "There's not much to code because it's a book list, but it's readable. ", "Q1_codable" : "1" } ] } }, { "index" : 13, "labels" : { "micspa" : [ { "created_at" : { "$date" : 1342448558362 }, "Q3_essay" : "", "Q1_codable" : "1" } ] } }, { "index" : 88, "labels" : { "micspa" : [ { "created_at" : { "$date" : 1342448571231 }, "Q3_essay" : "It seems like there should be one or two more paragraphs at the end of this news story", "Q1_codable" : "2" } ] } }, { "index" : 97, "labels" : { "micspa" : [ { "created_at" : { "$date" : 1342448590399 }, "Q3_essay" : "", "Q1_codable" : "1" } ] } }, { "index" : 169, "labels" : { "micspa" : [ { "created_at" : { "$date" : 1342448648535 }, "Q3_essay" : "There are some spacing errors throughout the article that make some parts of the article a little confusing", "Q1_codable" : "2" } ] } }, { "index" : 122, "labels" : { "admin" : [], "aleyz" : [ { "created_at" : { "$date" : 1342510546132 }, "Q2_problem_type" : "1", "Q3_essay" : "It's just a list of births from public records. ", "Q1_codable" : "3" } ], "micspa" : [ { "created_at" : { "$date" : 1342448655569 }, "Q3_essay" : "", "Q1_codable" : "1" } ] } }, { "index" : 51, "labels" : { "aleyz" : [ { "created_at" : { "$date" : 1342510583884 }, "Q3_essay" : "", "Q1_codable" : "1" } ] } }, { "index" : 94, "labels" : { "micspa" : [ { "created_at" : { "$date" : 1342448674796 }, "Q3_essay" : "", "Q1_codable" : "1" } ] } }, { "index" : 162, "labels" : { "aleyz" : [ { "created_at" : { "$date" : 1342510639048 }, "Q3_essay" : "", "Q1_codable" : "1" } ] } }, { "index" : 110, "labels" : { "admin" : [] } }, { "index" : 37, "labels" : { "micspa" : [ { "created_at" : { "$date" : 1342448679212 }, "Q3_essay" : "", "Q1_codable" : "1" } ] } }, { "index" : 124, "labels" : { "admin" : [], "aleyz" : [ { "created_at" : { "$date" : 1342510697457 }, "Q3_essay" : "", "Q1_codable" : "1" } ], "micspa" : [ { "created_at" : { "$date" : 1342448684351 }, "Q3_essay" : "", "Q1_codable" : "1" } ] } }, { "index" : 126, "labels" : { "aleyz" : [ { "created_at" : { "$date" : 1342510728843 }, "Q3_essay" : "", "Q1_codable" : "1" } ] } }, { "index" : 10, "labels" : { "micspa" : [ { "created_at" : { "$date" : 1342448690354 }, "Q3_essay" : "", "Q1_codable" : "1" } ] } }, { "index" : 56, "labels" : { "admin" : [], "aleyz" : [ { "created_at" : { "$date" : 1342510762238 }, "Q3_essay" : "", "Q1_codable" : "1" } ], "micspa" : [ { "created_at" : { "$date" : 1342448694425 }, "Q3_essay" : "", "Q1_codable" : "1" } ] } }, { "index" : 136, "labels" : { "admin" : [], "aleyz" : [ { "created_at" : { "$date" : 1342510815650 }, "Q3_essay" : "", "Q1_codable" : "1" } ], "micspa" : [ { "created_at" : { "$date" : 1342448708365 }, "Q3_essay" : "", "Q1_codable" : "1" } ] } }, { "index" : 103, "labels" : { "micspa" : [ { "created_at" : { "$date" : 1342448713986 }, "Q3_essay" : "", "Q1_codable" : "1" } ] } }, { "index" : 167, "labels" : { "admin" : [] } }, { "index" : 127, "labels" : { "admin" : [], "aleyz" : [ { "created_at" : { "$date" : 1342510882696 }, "Q3_essay" : "The paragraph breaks are a little off but it's still readable. ", "Q1_codable" : "1" } ], "micspa" : [ { "created_at" : { "$date" : 1342448758790 }, "Q3_essay" : "There are some spacing errors throughout the article that sometimes make the article a little confusing.  Also, it seems like there should be one or two more paragraphs at the end of this news story.", "Q1_codable" : "2" } ] } }, { "index" : 134, "labels" : { "admin" : [], "aleyz" : [ { "created_at" : { "$date" : 1342510907427 }, "Q3_essay" : "", "Q1_codable" : "1" } ], "micspa" : [ { "created_at" : { "$date" : 1342448844286 }, "Q2_problem_type" : "2", "Q3_essay" : "", "Q1_codable" : "2" } ] } }, { "index" : 44, "labels" : { "admin" : [] } }, { "index" : 132, "labels" : { "aleyz" : [ { "created_at" : { "$date" : 1342510953202 }, "Q2_problem_type" : "2", "Q3_essay" : "", "Q1_codable" : "3" } ] } }, { "index" : 36, "labels" : { "aleyz" : [ { "created_at" : { "$date" : 1342510964011 }, "Q3_essay" : "", "Q1_codable" : "1" } ] } }, { "index" : 26, "labels" : { "admin" : [], "aleyz" : [ { "created_at" : { "$date" : 1342510986113 }, "Q3_essay" : "", "Q1_codable" : "1" } ], "micspa" : [ { "created_at" : { "$date" : 1342448863303 }, "Q3_essay" : "", "Q1_codable" : "1" } ] } }, { "index" : 123, "labels" : { "aleyz" : [ { "created_at" : { "$date" : 1342510996937 }, "Q3_essay" : "", "Q1_codable" : "1" } ] } }, { "index" : 77, "labels" : { "admin" : [] } }, { "index" : 166, "labels" : { "admin" : [], "aleyz" : [ { "created_at" : { "$date" : 1342511083710 }, "Q3_essay" : "", "Q1_codable" : "1" } ], "micspa" : [ { "created_at" : { "$date" : 1342448870775 }, "Q3_essay" : "", "Q1_codable" : "1" } ] } }, { "index" : 107, "labels" : { "admin" : [] } }, { "index" : 62, "labels" : { "admin" : [] } }, { "index" : 114, "labels" : { "aleyz" : [ { "created_at" : { "$date" : 1342511091209 }, "Q3_essay" : "", "Q1_codable" : "1" } ] } }, { "index" : 89, "labels" : { "admin" : [] } }, { "index" : 67, "labels" : { "admin" : [], "aleyz" : [ { "created_at" : { "$date" : 1342511119967 }, "Q3_essay" : "", "Q1_codable" : "1" } ], "micspa" : [ { "created_at" : { "$date" : 1342448940564 }, "Q3_essay" : "It seems like the third paragraph is missing a few words.  Also, it seems like there should be a few more paragraphs at the end of the article.", "Q1_codable" : "2" } ] } }, { "index" : 70, "labels" : { "admin" : [], "aleyz" : [ { "created_at" : { "$date" : 1342511208522 }, "Q3_essay" : "", "Q1_codable" : "1" } ], "micspa" : [ { "created_at" : { "$date" : 1342448944395 }, "Q3_essay" : "", "Q1_codable" : "1" } ] } }, { "index" : 144, "labels" : { "admin" : [], "aleyz" : [ { "created_at" : { "$date" : 1342511275205 }, "Q3_essay" : "", "Q1_codable" : "1" } ], "micspa" : [ { "created_at" : { "$date" : 1342448957632 }, "Q3_essay" : "", "Q1_codable" : "1" } ] } }, { "index" : 63, "labels" : { "aleyz" : [ { "created_at" : { "$date" : 1342511284859 }, "Q3_essay" : "", "Q1_codable" : "1" } ] } }, { "index" : 31, "labels" : { "micspa" : [ { "created_at" : { "$date" : 1342448964991 }, "Q3_essay" : "", "Q1_codable" : "1" } ] } }, { "index" : 11, "labels" : { "admin" : [], "aleyz" : [ { "created_at" : { "$date" : 1342511306709 }, "Q3_essay" : "", "Q1_codable" : "1" } ], "micspa" : [ { "created_at" : { "$date" : 1342449025531 }, "Q3_essay" : "", "Q1_codable" : "1" } ] } }, { "index" : 14, "labels" : { "admin" : [], "aleyz" : [ { "created_at" : { "$date" : 1342511379337 }, "Q3_essay" : "", "Q1_codable" : "1" } ], "micspa" : [ { "created_at" : { "$date" : 1342449029585 }, "Q3_essay" : "", "Q1_codable" : "1" } ] } }, { "index" : 117, "labels" : { "aleyz" : [ { "created_at" : { "$date" : 1342511405382 }, "Q3_essay" : "", "Q1_codable" : "1" } ] } }, { "index" : 135, "labels" : { "admin" : [], "aleyz" : [ { "created_at" : { "$date" : 1342511454226 }, "Q3_essay" : "", "Q1_codable" : "1" } ], "micspa" : [ { "created_at" : { "$date" : 1342449032320 }, "Q3_essay" : "", "Q1_codable" : "1" } ] } }, { "index" : 109, "labels" : { "micspa" : [ { "created_at" : { "$date" : 1342449039485 }, "Q3_essay" : "", "Q1_codable" : "1" } ] } }, { "index" : 91, "labels" : { "micspa" : [ { "created_at" : { "$date" : 1342449052945 }, "Q3_essay" : "", "Q1_codable" : "1" } ] } }, { "index" : 78, "labels" : { "aleyz" : [ { "created_at" : { "$date" : 1342511516043 }, "Q3_essay" : "The subheadings of the text are not separate from text but it's still readable", "Q1_codable" : "1" } ] } }, { "index" : 113, "labels" : { "admin" : [] } }, { "index" : 33, "labels" : { "admin" : [], "aleyz" : [ { "created_at" : { "$date" : 1342511553572 }, "Q3_essay" : "", "Q1_codable" : "1" } ], "micspa" : [ { "created_at" : { "$date" : 1342449061917 }, "Q3_essay" : "", "Q1_codable" : "1" } ] } }, { "index" : 98, "labels" : { "admin" : [] } }, { "index" : 68, "labels" : { "admin" : [], "aleyz" : [ { "created_at" : { "$date" : 1342511566292 }, "Q3_essay" : "", "Q1_codable" : "1" } ], "micspa" : [ { "created_at" : { "$date" : 1342449066511 }, "Q3_essay" : "", "Q1_codable" : "1" } ] } }, { "index" : 151, "labels" : { "micspa" : [ { "created_at" : { "$date" : 1342449071959 }, "Q3_essay" : "", "Q1_codable" : "1" } ] } }, { "index" : 95, "labels" : { "admin" : [] } }, { "index" : 139, "labels" : { "micspa" : [ { "created_at" : { "$date" : 1342449080811 }, "Q2_problem_type" : "1", "Q3_essay" : "", "Q1_codable" : "3" } ] } }, { "index" : 7, "labels" : { "micspa" : [ { "created_at" : { "$date" : 1342449086745 }, "Q3_essay" : "", "Q1_codable" : "1" } ] } }, { "index" : 32, "labels" : { "admin" : [] } }, { "index" : 130, "labels" : { "admin" : [], "aleyz" : [ { "created_at" : { "$date" : 1342511593096 }, "Q3_essay" : "", "Q1_codable" : "1" } ], "micspa" : [ { "created_at" : { "$date" : 1342449090569 }, "Q3_essay" : "", "Q1_codable" : "1" } ] } }, { "index" : 45, "labels" : { "admin" : [], "aleyz" : [ { "created_at" : { "$date" : 1342511609480 }, "Q3_essay" : "", "Q1_codable" : "1" } ], "micspa" : [ { "created_at" : { "$date" : 1342449111381 }, "Q3_essay" : "", "Q1_codable" : "1" } ] } }, { "index" : 74, "labels" : { "admin" : [], "aleyz" : [ { "created_at" : { "$date" : 1342511614629 }, "Q3_essay" : "", "Q1_codable" : "1" } ], "micspa" : [ { "created_at" : { "$date" : 1342449114491 }, "Q3_essay" : "", "Q1_codable" : "1" } ] } }, { "index" : 146, "labels" : { "admin" : [], "aleyz" : [ { "created_at" : { "$date" : 1342511679368 }, "Q3_essay" : "", "Q1_codable" : "1" } ], "micspa" : [ { "created_at" : { "$date" : 1342449236626 }, "Q3_essay" : "It seems like there should be one or two more paragraphs at the end of this article", "Q1_codable" : "2" } ] } }, { "index" : 101, "labels" : { "admin" : [], "aleyz" : [ { "created_at" : { "$date" : 1342511855681 }, "Q3_essay" : "Multiple issues addressed in the text that aren't referenced by the header", "Q1_codable" : "1" } ], "micspa" : [ { "created_at" : { "$date" : 1342449239993 }, "Q3_essay" : "", "Q1_codable" : "1" } ] } }, { "index" : 19, "labels" : { "micspa" : [ { "created_at" : { "$date" : 1342449246645 }, "Q3_essay" : "", "Q1_codable" : "1" } ] } }, { "index" : 131, "labels" : { "admin" : [], "aleyz" : [ { "created_at" : { "$date" : 1342511865185 }, "Q3_essay" : "", "Q1_codable" : "1" } ], "micspa" : [ { "created_at" : { "$date" : 1342449256790 }, "Q3_essay" : "", "Q1_codable" : "1" } ] } }, { "index" : 84, "labels" : { "admin" : [], "aleyz" : [ { "created_at" : { "$date" : 1342511922243 }, "Q3_essay" : "", "Q1_codable" : "1" } ], "micspa" : [ { "created_at" : { "$date" : 1342449341360 }, "Q3_essay" : "It seems like there should be one or two more paragraphs at the end of this news story", "Q1_codable" : "2" } ] } }, { "index" : 27, "labels" : { "aleyz" : [ { "created_at" : { "$date" : 1342511934312 }, "Q3_essay" : "", "Q1_codable" : "1" } ] } }, { "index" : 96, "labels" : { "admin" : [], "aleyz" : [ { "created_at" : { "$date" : 1342511950465 }, "Q3_essay" : "", "Q1_codable" : "1" } ], "micspa" : [ { "created_at" : { "$date" : 1342449344675 }, "Q3_essay" : "", "Q1_codable" : "1" } ] } }, { "index" : 129, "labels" : { "aleyz" : [ { "created_at" : { "$date" : 1342511957595 }, "Q2_problem_type" : "1", "Q3_essay" : "", "Q1_codable" : "3" } ] } }, { "index" : 0, "labels" : { "aleyz" : [ { "created_at" : { "$date" : 1342511968134 }, "Q3_essay" : "", "Q1_codable" : "1" } ] } }, { "index" : 147, "labels" : { "aleyz" : [ { "created_at" : { "$date" : 1342511986305 }, "Q3_essay" : "", "Q1_codable" : "1" } ] } }, { "index" : 105, "labels" : { "admin" : [], "aleyz" : [ { "created_at" : { "$date" : 1342512108903 }, "Q3_essay" : "", "Q1_codable" : "1" } ], "micspa" : [ { "created_at" : { "$date" : 1342449349884 }, "Q3_essay" : "", "Q1_codable" : "1" } ] } }, { "index" : 23, "labels" : { "admin" : [] } }, { "index" : 112, "labels" : { "micspa" : [ { "created_at" : { "$date" : 1342449375797 }, "Q3_essay" : "There's a minor spacing error after the second paragraph", "Q1_codable" : "2" } ] } }, { "index" : 155, "labels" : { "admin" : [], "aleyz" : [ { "created_at" : { "$date" : 1342512139355 }, "Q3_essay" : "", "Q1_codable" : "1" } ], "micspa" : [ { "created_at" : { "$date" : 1342449379189 }, "Q3_essay" : "", "Q1_codable" : "1" } ] } }, { "index" : 43, "labels" : { "micspa" : [ { "created_at" : { "$date" : 1342449386971 }, "Q3_essay" : "", "Q1_codable" : "1" } ] } }, { "index" : 156, "labels" : { "admin" : [], "aleyz" : [ { "created_at" : { "$date" : 1342512232294 }, "Q3_essay" : "", "Q1_codable" : "1" } ], "micspa" : [ { "created_at" : { "$date" : 1342449390289 }, "Q3_essay" : "", "Q1_codable" : "1" } ] } }, { "index" : 59, "labels" : { "admin" : [] } }, { "index" : 15, "labels" : { "aleyz" : [ { "created_at" : { "$date" : 1342512267176 }, "Q3_essay" : "", "Q1_codable" : "1" } ] } }, { "index" : 81, "labels" : { "aleyz" : [ { "created_at" : { "$date" : 1342512308725 }, "Q3_essay" : "", "Q1_codable" : "1" } ] } }, { "index" : 140, "labels" : { "admin" : [] } }, { "index" : 90, "labels" : { "admin" : [], "aleyz" : [ { "created_at" : { "$date" : 1342512388751 }, "Q3_essay" : "", "Q1_codable" : "1" } ], "micspa" : [ { "created_at" : { "$date" : 1342449394209 }, "Q3_essay" : "", "Q1_codable" : "1" } ] } }, { "index" : 150, "labels" : { "aleyz" : [ { "created_at" : { "$date" : 1342512409131 }, "Q3_essay" : "", "Q1_codable" : "1" } ] } }, { "index" : 3, "labels" : { "aleyz" : [ { "created_at" : { "$date" : 1342512461584 }, "Q3_essay" : "Not much content because it's a clarification but i think it will be ok", "Q1_codable" : "1" } ] } }, { "index" : 22, "labels" : { "micspa" : [ { "created_at" : { "$date" : 1342449398819 }, "Q3_essay" : "", "Q1_codable" : "1" } ] } }, { "index" : 83, "labels" : { "admin" : [], "aleyz" : [ { "created_at" : { "$date" : 1342512466781 }, "Q2_problem_type" : "1", "Q3_essay" : "", "Q1_codable" : "3" } ], "micspa" : [ { "created_at" : { "$date" : 1342449404325 }, "Q2_problem_type" : "1", "Q3_essay" : "", "Q1_codable" : "3" } ] } }, { "index" : 172, "labels" : { "micspa" : [ { "created_at" : { "$date" : 1342449418408 }, "Q3_essay" : "", "Q1_codable" : "1" } ] } }, { "index" : 38, "labels" : { "admin" : [], "aleyz" : [ { "created_at" : { "$date" : 1342512566019 }, "Q3_essay" : "", "Q1_codable" : "1" } ], "micspa" : [ { "created_at" : { "$date" : 1342449422193 }, "Q3_essay" : "", "Q1_codable" : "1" } ] } }, { "index" : 148, "labels" : { "micspa" : [ { "created_at" : { "$date" : 1342449425883 }, "Q3_essay" : "", "Q1_codable" : "1" } ] } }, { "index" : 87, "labels" : { "aleyz" : [ { "created_at" : { "$date" : 1342512580143 }, "Q3_essay" : "", "Q1_codable" : "1" } ] } }, { "index" : 85, "labels" : { "micspa" : [ { "created_at" : { "$date" : 1342449479166 }, "Q3_essay" : "It seems like there should be one or two more paragraphs at the end of this article", "Q1_codable" : "2" } ] } }, { "index" : 35, "labels" : { "admin" : [], "aleyz" : [ { "created_at" : { "$date" : 1342512650567 }, "Q3_essay" : "The header seems off as does the first paragraph, however, it's still readable and easy to code. ", "Q1_codable" : "1" } ], "micspa" : [ { "created_at" : { "$date" : 1342449511008 }, "Q3_essay" : "The first paragraph is missing a few words", "Q1_codable" : "2" } ] } }, { "index" : 4, "labels" : { "micspa" : [ { "created_at" : { "$date" : 1342449518441 }, "Q3_essay" : "", "Q1_codable" : "1" } ] } }, { "index" : 79, "labels" : { "admin" : [], "aleyz" : [ { "created_at" : { "$date" : 1342512665167 }, "Q3_essay" : "", "Q1_codable" : "1" } ], "micspa" : [ { "created_at" : { "$date" : 1342449526489 }, "Q3_essay" : "", "Q1_codable" : "1" } ] } }, { "index" : 170, "labels" : { "admin" : [], "aleyz" : [ { "created_at" : { "$date" : 1342512684006 }, "Q3_essay" : "", "Q1_codable" : "1" } ], "micspa" : [ { "created_at" : { "$date" : 1342449532119 }, "Q3_essay" : "", "Q1_codable" : "1" } ] } } ], "reports" : { "progress" : { "coders" : { "admin" : { "assigned" : 104, "percent" : 0, "complete" : 0 }, "aleyz" : { "assigned" : 110, "percent" : 100, "complete" : 110 }, "micspa" : { "assigned" : 110, "percent" : 100, "complete" : 110 } }, "summary" : { "assigned" : 324, "percent" : 67.90000000000001, "complete" : 220 } }, "reliability" : {} } },{ "_id" : { "$oid" : "5005a6fb33679d0c5f9be6c8" }, "profile" : { "coders" : [ "aleyz", "micspa", "admin" ], "index" : 4, "shuffle" : false, "name" : "Batch 4", "created_at" : { "$date" : 1342529707218 }, "codebook_id" : { "$oid" : "5005a43533679d0c5f9be6c6" }, "collection_id" : { "$oid" : "5005a6e933679d0c5f9be6c7" }, "pct_overlap" : 100, "description" : "News sample C * Neutral voice (2)" }, "documents" : [ { "index" : 0, "labels" : { "admin" : [], "aleyz" : [ { "created_at" : { "$date" : 1342532381072 }, "Q2_notes" : "The last paragraph repeats itself and seems a bit odd. ", "Q1_neutral" : "1" }, { "created_at" : { "$date" : 1342594422815 }, "Q2_notes" : "No text" }, { "created_at" : { "$date" : 1342594424898 }, "Q2_notes" : "" } ], "micspa" : [ { "created_at" : { "$date" : 1342543228129 }, "Q2_notes" : "", "Q1_neutral" : "1" } ] } }, { "index" : 1, "labels" : { "admin" : [], "aleyz" : [ { "created_at" : { "$date" : 1342565722005 }, "Q2_notes" : "", "Q1_neutral" : "2" } ], "micspa" : [ { "created_at" : { "$date" : 1342543250669 }, "Q2_notes" : "", "Q1_neutral" : "2" } ] } }, { "index" : 2, "labels" : { "admin" : [], "aleyz" : [ { "created_at" : { "$date" : 1342565802976 }, "Q2_notes" : "The text is not readable because of a formatting issue. " } ], "micspa" : [ { "created_at" : { "$date" : 1342543275437 }, "Q2_notes" : "", "Q1_neutral" : "2" } ] } }, { "index" : 3, "labels" : { "admin" : [], "aleyz" : [ { "created_at" : { "$date" : 1342566070680 }, "Q2_notes" : "", "Q1_neutral" : "1" } ], "micspa" : [ { "created_at" : { "$date" : 1342543302426 }, "Q2_notes" : "", "Q1_neutral" : "1" } ] } }, { "index" : 4, "labels" : { "admin" : [], "aleyz" : [ { "created_at" : { "$date" : 1342566459563 }, "Q2_notes" : "", "Q1_neutral" : "1" } ], "micspa" : [ { "created_at" : { "$date" : 1342543331050 }, "Q2_notes" : "", "Q1_neutral" : "2" } ] } }, { "index" : 5, "labels" : { "admin" : [], "aleyz" : [ { "created_at" : { "$date" : 1342566505250 }, "Q2_notes" : "", "Q1_neutral" : "2" } ], "micspa" : [ { "created_at" : { "$date" : 1342543343562 }, "Q2_notes" : "", "Q1_neutral" : "2" } ] } }, { "index" : 6, "labels" : { "admin" : [], "aleyz" : [ { "created_at" : { "$date" : 1342566629256 }, "Q2_notes" : "", "Q1_neutral" : "1" } ], "micspa" : [ { "created_at" : { "$date" : 1342543352783 }, "Q2_notes" : "", "Q1_neutral" : "1" } ] } }, { "index" : 7, "labels" : { "admin" : [], "aleyz" : [ { "created_at" : { "$date" : 1342566703795 }, "Q2_notes" : "", "Q1_neutral" : "1" } ], "micspa" : [ { "created_at" : { "$date" : 1342543360421 }, "Q2_notes" : "", "Q1_neutral" : "1" } ] } }, { "index" : 8, "labels" : { "admin" : [], "aleyz" : [ { "created_at" : { "$date" : 1342566795499 }, "Q2_notes" : "", "Q1_neutral" : "2" } ], "micspa" : [ { "created_at" : { "$date" : 1342543381207 }, "Q2_notes" : "", "Q1_neutral" : "2" } ] } }, { "index" : 9, "labels" : { "admin" : [], "aleyz" : [ { "created_at" : { "$date" : 1342593582338 }, "Q2_notes" : "", "Q1_neutral" : "2" } ], "micspa" : [ { "created_at" : { "$date" : 1342543382532 }, "Q2_notes" : "" } ] } }, { "index" : 10, "labels" : { "admin" : [], "aleyz" : [ { "created_at" : { "$date" : 1342593637383 }, "Q2_notes" : "", "Q1_neutral" : "1" } ], "micspa" : [ { "created_at" : { "$date" : 1342543392795 }, "Q2_notes" : "", "Q1_neutral" : "2" } ] } }, { "index" : 11, "labels" : { "admin" : [], "aleyz" : [ { "created_at" : { "$date" : 1342593835326 }, "Q2_notes" : "The author never explicitly expresses an opinion but it is present. ", "Q1_neutral" : "2" } ], "micspa" : [ { "created_at" : { "$date" : 1342543405231 }, "Q2_notes" : "", "Q1_neutral" : "2" } ] } }, { "index" : 12, "labels" : { "admin" : [], "aleyz" : [ { "created_at" : { "$date" : 1342593846272 }, "Q2_notes" : "", "Q1_neutral" : "1" } ], "micspa" : [ { "created_at" : { "$date" : 1342543412313 }, "Q2_notes" : "", "Q1_neutral" : "1" } ] } }, { "index" : 13, "labels" : { "admin" : [], "aleyz" : [ { "created_at" : { "$date" : 1342593870006 }, "Q2_notes" : "", "Q1_neutral" : "1" } ], "micspa" : [ { "created_at" : { "$date" : 1342543439389 }, "Q2_notes" : "", "Q1_neutral" : "1" } ] } }, { "index" : 14, "labels" : { "admin" : [], "aleyz" : [ { "created_at" : { "$date" : 1342593878418 }, "Q2_notes" : "No text. " } ], "micspa" : [ { "created_at" : { "$date" : 1342543440911 }, "Q2_notes" : "" } ] } }, { "index" : 15, "labels" : { "admin" : [], "aleyz" : [ { "created_at" : { "$date" : 1342594000597 }, "Q2_notes" : "", "Q1_neutral" : "1" } ], "micspa" : [ { "created_at" : { "$date" : 1342543482851 }, "Q2_notes" : "", "Q1_neutral" : "2" } ] } }, { "index" : 16, "labels" : { "admin" : [], "aleyz" : [ { "created_at" : { "$date" : 1342594020670 }, "Q2_notes" : "", "Q1_neutral" : "1" } ], "micspa" : [ { "created_at" : { "$date" : 1342543487244 }, "Q2_notes" : "", "Q1_neutral" : "1" } ] } }, { "index" : 17, "labels" : { "admin" : [], "aleyz" : [ { "created_at" : { "$date" : 1342594277883 }, "Q2_notes" : "The first sentence reads a bit more opinionated, but overall the text seems neutral", "Q1_neutral" : "1" } ], "micspa" : [ { "created_at" : { "$date" : 1342543601948 }, "Q2_notes" : "", "Q1_neutral" : "2" } ] } }, { "index" : 18, "labels" : { "admin" : [], "aleyz" : [ { "created_at" : { "$date" : 1342594383014 }, "Q2_notes" : "", "Q1_neutral" : "2" } ], "micspa" : [ { "created_at" : { "$date" : 1342543610783 }, "Q2_notes" : "", "Q1_neutral" : "2" } ] } }, { "index" : 19, "labels" : { "admin" : [], "aleyz" : [ { "created_at" : { "$date" : 1342594389290 }, "Q2_notes" : "", "Q1_neutral" : "1" }, { "created_at" : { "$date" : 1342594395089 }, "Q2_notes" : "", "Q1_neutral" : "1" } ], "micspa" : [ { "created_at" : { "$date" : 1342543613677 }, "Q2_notes" : "", "Q1_neutral" : "1" } ] } } ], "reports" : { "progress" : { "coders" : { "admin" : { "assigned" : 20, "percent" : 0, "complete" : 0 }, "aleyz" : { "assigned" : 20, "percent" : 100, "complete" : 20 }, "micspa" : { "assigned" : 20, "percent" : 100, "complete" : 20 } }, "summary" : { "assigned" : 60, "percent" : 66.7, "complete" : 40 } }, "reliability" : {} } },{ "_id" : { "$oid" : "5005a70b33679d0c5f9be6c9" }, "profile" : { "coders" : [ "aleyz", "micspa", "admin" ], "index" : 5, "shuffle" : false, "name" : "Batch 5", "created_at" : { "$date" : 1342529723257 }, "codebook_id" : { "$oid" : "5005a37733679d0c5f9be6c4" }, "collection_id" : { "$oid" : "5005a6e933679d0c5f9be6c7" }, "pct_overlap" : 100, "description" : "News sample C * Public Import (5)" }, "documents" : [ { "index" : 0, "labels" : { "admin" : [], "aleyz" : [ { "created_at" : { "$date" : 1342594465579 }, "Q3_notes" : "", "Q2_publicimport2" : "1", "Q1_publicimport1" : "1" } ], "micspa" : [ { "created_at" : { "$date" : 1342541693775 }, "Q3_notes" : "", "Q2_publicimport2" : "1", "Q1_publicimport1" : "3" } ] } }, { "index" : 1, "labels" : { "admin" : [], "aleyz" : [ { "created_at" : { "$date" : 1342594506836 }, "Q3_notes" : "", "Q2_publicimport2" : "1", "Q1_publicimport1" : "1" } ], "micspa" : [ { "created_at" : { "$date" : 1342541703814 }, "Q3_notes" : "", "Q2_publicimport2" : "1", "Q1_publicimport1" : "3" } ] } }, { "index" : 2, "labels" : { "admin" : [], "aleyz" : [ { "created_at" : { "$date" : 1342594559112 }, "Q3_notes" : "The formatting is off and makes the text nearly unreadable. ", "Q2_publicimport2" : "1", "Q1_publicimport1" : "1" } ], "micspa" : [ { "created_at" : { "$date" : 1342541713423 }, "Q3_notes" : "", "Q2_publicimport2" : "1", "Q1_publicimport1" : "1" } ] } }, { "index" : 3, "labels" : { "admin" : [], "aleyz" : [ { "created_at" : { "$date" : 1342594736337 }, "Q3_notes" : "It seems like the author is suggesting both a group response by an oversight board and a governmental response by government officials. ", "Q2_publicimport2" : "4", "Q1_publicimport1" : "2" } ], "micspa" : [ { "created_at" : { "$date" : 1342541764951 }, "Q3_notes" : "", "Q2_publicimport2" : "3", "Q1_publicimport1" : "6" } ] } }, { "index" : 4, "labels" : { "admin" : [], "aleyz" : [ { "created_at" : { "$date" : 1342595148773 }, "Q3_notes" : "This topic requires that all residents of NJ comply with a new law. Would this be a group response or is this an individual issue in which people decide whether to comply or not? Also, this new law is a governmental response to the negative effects of fertilizer. The response has already taken place so does that mean it still \"requires a response\"?", "Q2_publicimport2" : "4", "Q1_publicimport1" : "2" } ], "micspa" : [ { "created_at" : { "$date" : 1342541853032 }, "Q3_notes" : "", "Q2_publicimport2" : "4", "Q1_publicimport1" : "6" } ] } }, { "index" : 5, "labels" : { "admin" : [], "aleyz" : [ { "created_at" : { "$date" : 1342595379839 }, "Q3_notes" : "It's hard to assess the impact of a religious figure on people taking into account different religions and non-believers. ", "Q2_publicimport2" : "1", "Q1_publicimport1" : "4" } ], "micspa" : [ { "created_at" : { "$date" : 1342542099770 }, "Q3_notes" : "", "Q2_publicimport2" : "2", "Q1_publicimport1" : "5" } ] } }, { "index" : 6, "labels" : { "admin" : [], "aleyz" : [ { "created_at" : { "$date" : 1342595397409 }, "Q3_notes" : "", "Q2_publicimport2" : "1", "Q1_publicimport1" : "1" } ], "micspa" : [ { "created_at" : { "$date" : 1342542170671 }, "Q3_notes" : "", "Q2_publicimport2" : "1", "Q1_publicimport1" : "2" } ] } }, { "index" : 7, "labels" : { "admin" : [], "aleyz" : [ { "created_at" : { "$date" : 1342595422385 }, "Q3_notes" : "", "Q2_publicimport2" : "1", "Q1_publicimport1" : "2" } ], "micspa" : [ { "created_at" : { "$date" : 1342542225595 }, "Q3_notes" : "", "Q2_publicimport2" : "3", "Q1_publicimport1" : "5" } ] } }, { "index" : 8, "labels" : { "admin" : [], "aleyz" : [ { "created_at" : { "$date" : 1342595483797 }, "Q3_notes" : "", "Q2_publicimport2" : "1", "Q1_publicimport1" : "1" } ], "micspa" : [ { "created_at" : { "$date" : 1342542406173 }, "Q3_notes" : "", "Q2_publicimport2" : "1", "Q1_publicimport1" : "2" } ] } }, { "index" : 9, "labels" : { "admin" : [], "aleyz" : [ { "created_at" : { "$date" : 1342595542041 }, "Q3_notes" : "", "Q2_publicimport2" : "1", "Q1_publicimport1" : "1" } ], "micspa" : [ { "created_at" : { "$date" : 1342542457989 }, "Q3_notes" : "", "Q2_publicimport2" : "1", "Q1_publicimport1" : "3" } ] } }, { "index" : 10, "labels" : { "admin" : [], "aleyz" : [ { "created_at" : { "$date" : 1342595619250 }, "Q3_notes" : "", "Q2_publicimport2" : "1", "Q1_publicimport1" : "4" } ], "micspa" : [ { "created_at" : { "$date" : 1342542604548 }, "Q3_notes" : "", "Q2_publicimport2" : "2", "Q1_publicimport1" : "5" } ] } }, { "index" : 11, "labels" : { "admin" : [], "aleyz" : [ { "created_at" : { "$date" : 1342595631031 }, "Q3_notes" : "", "Q2_publicimport2" : "1", "Q1_publicimport1" : "1" } ], "micspa" : [ { "created_at" : { "$date" : 1342542749688 }, "Q3_notes" : "", "Q2_publicimport2" : "1", "Q1_publicimport1" : "2" } ] } }, { "index" : 12, "labels" : { "admin" : [], "aleyz" : [ { "created_at" : { "$date" : 1342595643938 }, "Q3_notes" : "", "Q2_publicimport2" : "1", "Q1_publicimport1" : "1" } ], "micspa" : [ { "created_at" : { "$date" : 1342542761941 }, "Q3_notes" : "", "Q2_publicimport2" : "1", "Q1_publicimport1" : "1" } ] } }, { "index" : 13, "labels" : { "admin" : [], "aleyz" : [ { "created_at" : { "$date" : 1342595653844 }, "Q3_notes" : "", "Q2_publicimport2" : "1", "Q1_publicimport1" : "1" } ], "micspa" : [ { "created_at" : { "$date" : 1342542770865 }, "Q3_notes" : "", "Q2_publicimport2" : "1", "Q1_publicimport1" : "1" } ] } }, { "index" : 14, "labels" : { "admin" : [], "aleyz" : [ { "created_at" : { "$date" : 1342595660659 }, "Q3_notes" : "No text" } ], "micspa" : [ { "created_at" : { "$date" : 1342542775448 }, "Q3_notes" : "" } ] } }, { "index" : 15, "labels" : { "admin" : [], "aleyz" : [ { "created_at" : { "$date" : 1342595756188 }, "Q3_notes" : "This article is about the individual decision to donate bone marrow, but highlights the need for ethnic minority donors which is perhaps a group response. ", "Q2_publicimport2" : "2", "Q1_publicimport1" : "2" } ], "micspa" : [ { "created_at" : { "$date" : 1342542849020 }, "Q3_notes" : "", "Q2_publicimport2" : "2", "Q1_publicimport1" : "3" } ] } }, { "index" : 16, "labels" : { "admin" : [], "aleyz" : [ { "created_at" : { "$date" : 1342595766076 }, "Q3_notes" : "", "Q2_publicimport2" : "1", "Q1_publicimport1" : "1" } ], "micspa" : [ { "created_at" : { "$date" : 1342542857460 }, "Q3_notes" : "", "Q2_publicimport2" : "1", "Q1_publicimport1" : "1" } ] } }, { "index" : 17, "labels" : { "admin" : [], "aleyz" : [ { "created_at" : { "$date" : 1342595774102 }, "Q3_notes" : "", "Q2_publicimport2" : "1", "Q1_publicimport1" : "1" } ], "micspa" : [ { "created_at" : { "$date" : 1342543004172 }, "Q3_notes" : "", "Q2_publicimport2" : "1", "Q1_publicimport1" : "2" } ] } }, { "index" : 18, "labels" : { "admin" : [], "aleyz" : [ { "created_at" : { "$date" : 1342595793105 }, "Q3_notes" : "", "Q2_publicimport2" : "1", "Q1_publicimport1" : "1" } ], "micspa" : [ { "created_at" : { "$date" : 1342543023452 }, "Q3_notes" : "", "Q2_publicimport2" : "2", "Q1_publicimport1" : "1" } ] } }, { "index" : 19, "labels" : { "admin" : [], "aleyz" : [ { "created_at" : { "$date" : 1342595800258 }, "Q3_notes" : "", "Q2_publicimport2" : "1", "Q1_publicimport1" : "1" } ], "micspa" : [ { "created_at" : { "$date" : 1342543029373 }, "Q3_notes" : "", "Q2_publicimport2" : "1", "Q1_publicimport1" : "1" } ] } } ], "reports" : { "progress" : { "coders" : { "admin" : { "assigned" : 20, "percent" : 0, "complete" : 0 }, "aleyz" : { "assigned" : 20, "percent" : 100, "complete" : 20 }, "micspa" : { "assigned" : 20, "percent" : 100, "complete" : 20 } }, "summary" : { "assigned" : 60, "percent" : 66.7, "complete" : 40 } }, "reliability" : {} } }]
